CHANGELOG
MANIFEST.in
README.md
README.txt
requirements
setup.py
AQoPA.egg-info/PKG-INFO
AQoPA.egg-info/SOURCES.txt
AQoPA.egg-info/dependency_links.txt
AQoPA.egg-info/entry_points.txt
AQoPA.egg-info/requires.txt
AQoPA.egg-info/top_level.txt
aqopa/__init__.py
aqopa/app.py
aqopa/cmd.py
aqopa/bin/__init__.py
aqopa/bin/console.py
aqopa/bin/gui.py
aqopa/bin/assets/PuzzlePiece.png
aqopa/bin/assets/PuzzlePieces.png
aqopa/bin/assets/about.png
aqopa/bin/assets/app_logo.png
aqopa/bin/assets/cash.png
aqopa/bin/assets/config.png
aqopa/bin/assets/energy.png
aqopa/bin/assets/exit.png
aqopa/bin/assets/gogreen.png
aqopa/bin/assets/lib.png
aqopa/bin/assets/logo.png
aqopa/bin/assets/metrics.png
aqopa/bin/assets/models_lib.png
aqopa/bin/assets/modules.png
aqopa/bin/assets/modules_results.png
aqopa/bin/assets/qop.png
aqopa/bin/assets/reputation.png
aqopa/bin/assets/results.png
aqopa/bin/assets/run.png
aqopa/bin/assets/versions.png
aqopa/gui/__init__.py
aqopa/gui/combo_check_box.py
aqopa/gui/general_purpose_frame_gui.py
aqopa/gui/main_frame_gui.py
aqopa/gui/main_notebook_gui.py
aqopa/gui/mmv_panel_gui.py
aqopa/gui/models_lib_gui.py
aqopa/gui/modules_panel_gui.py
aqopa/gui/results_panel_gui.py
aqopa/gui/run_panel_gui.py
aqopa/library/models/db-simultaneous-clients/meta.xml
aqopa/library/models/db-simultaneous-clients/metrics.qopml
aqopa/library/models/db-simultaneous-clients/model.qopml
aqopa/library/models/db-simultaneous-clients/versions.qopml
aqopa/library/models/qopml-comm/meta.xml
aqopa/library/models/qopml-comm/metrics.qopml
aqopa/library/models/qopml-comm/model.qopml
aqopa/library/models/qopml-comm/versions.qopml
aqopa/library/models/reputation-with-data-protection/meta.xml
aqopa/library/models/reputation-with-data-protection/metrics.qopml
aqopa/library/models/reputation-with-data-protection/model.qopml
aqopa/library/models/reputation-with-data-protection/versions.qopml
aqopa/library/models/roller-coaster/meta.xml
aqopa/library/models/roller-coaster/meta.xml~
aqopa/library/models/roller-coaster/metrics.qopml
aqopa/library/models/roller-coaster/model.qopml
aqopa/library/models/roller-coaster/versions.qopml
aqopa/library/models/wsn-join-network/meta.xml
